gridmap/__init__.py
gridmap/conf.py
gridmap/data.py
gridmap/job.py
gridmap/runner.py
gridmap/version.py
gridmap/web.py
gridmap-0.12.5.dist-info/DESCRIPTION.rst
gridmap-0.12.5.dist-info/entry_points.txt
gridmap-0.12.5.dist-info/METADATA
gridmap-0.12.5.dist-info/metadata.json
gridmap-0.12.5.dist-info/RECORD
gridmap-0.12.5.dist-info/top_level.txt
gridmap-0.12.5.dist-info/WHEEL
