Metadata-Version: 2.0
Name: gridmap
Version: 0.12.5
Summary: Easily map Python functions onto a cluster using a DRMAA-compatible grid engine like Sun Grid Engine (SGE).
Home-page: http://github.com/EducationalTestingService/gridmap
Author: Daniel Blanchard
Author-email: dblanchard@ets.org
License: GPL
Keywords: drmaa sge cluster distributed parallel
Platform: UNKNOWN
Classifier: Intended Audience :: Science/Research
Classifier: Intended Audience :: Developers
Classifier: License :: OSI Approved :: GNU General Public License v3 (GPLv3)
Classifier: Programming Language :: Python
Classifier: Topic :: Software Development
Classifier: Topic :: Scientific/Engineering
Classifier: Operating System :: POSIX
Classifier: Operating System :: Unix
Classifier: Operating System :: MacOS
Classifier: Programming Language :: Python :: 2
Classifier: Programming Language :: Python :: 2.7
Classifier: Programming Language :: Python :: 3
Classifier: Programming Language :: Python :: 3.3
Requires-Dist: drmaa
Requires-Dist: psutil
Requires-Dist: pyzmq
